oomol_cloud_task/__init__.py
oomol_cloud_task/client.py
oomol_cloud_task/errors.py
oomol_cloud_task/types.py
oomol_cloud_task_sdk-0.1.1.dist-info/METADATA
oomol_cloud_task_sdk-0.1.1.dist-info/WHEEL
oomol_cloud_task_sdk-0.1.1.dist-info/top_level.txt
oomol_cloud_task_sdk-0.1.1.dist-info/RECORD
