Metadata-Version: 2.4
Name: oomol-cloud-task-sdk
Version: 0.1.1
Summary: Python SDK for Oomol Cloud Task API
License-Expression: MIT
Requires-Python: >=3.7
Requires-Dist: requests>=2.25.0
